dovecotauth.py
dovecotauth-1.0.1.dist-info/LICENSE
dovecotauth-1.0.1.dist-info/WHEEL
dovecotauth-1.0.1.dist-info/METADATA
dovecotauth-1.0.1.dist-info/RECORD
