Metadata-Version: 2.1
Name: dovecotauth
Version: 1.0.1
Summary: A client library for the Dovecot Authentication Protocol v1.1
Home-page: https://github.com/kgaughan/dovecotauth
License: UNKNOWN
Author: Keith Gaughan
Author-email: k@stereochro.me
Requires-Python: >=3.3
Classifier: Development Status :: 4 - Beta
Classifier: Intended Audience :: System Administrators
Classifier: License :: OSI Approved :: MIT License
Classifier: Operating System :: POSIX
Classifier: Programming Language :: Python
Classifier: Programming Language :: Python :: 3
Classifier: Topic :: Communications :: Email :: Mail Transport Agents
Classifier: Topic :: Security
Classifier: Topic :: Utilities
Requires-Dist: passlib; extra == "dev"
Provides-Extra: dev
